pypassgen/__init__.py
pypassgen-0.1.0.dist-info/LICENSE
pypassgen-0.1.0.dist-info/METADATA
pypassgen-0.1.0.dist-info/WHEEL
pypassgen-0.1.0.dist-info/top_level.txt
pypassgen-0.1.0.dist-info/RECORD
