Metadata-Version: 2.1
Name: pypassgen
Version: 0.1.0
Summary: A python random password generator
Home-page: UNKNOWN
Author: Ashley Marando
Author-email: a.marando@me.com
License: UNKNOWN
Platform: UNKNOWN
Classifier: Programming Language :: Python :: 3
Classifier: License :: OSI Approved :: GNU General Public License v3 (GPLv3)
Classifier: Operating System :: OS Independent
